<?xml version="1.0"?>
<opencv_storage>
<globfeat type_id="opencv-matrix">
  <rows>1</rows>
  <cols>64</cols>
  <dt>f</dt>
  <data>
    0. 1.06948652e+01 9.23044739e+01 2.67900143e+01 0. 1.40532265e+01
    2.17885056e+01 1.14251528e+01 0. 5.88073444e+00 0. 0. 0. 0. 0. 0. 0.
    0. 0. 0. 0. 0. 0. 0. 0. 8.25416851e+00 0. 0. 0. 0. 0. 0. 0.
    1.54417334e+01 0. 0. 0. 0. 0. 0. 0. 0. 0. 0. 0. 0. 0. 0. 0.
    1.07092791e+01 1.55570412e+01 1.04594440e+01 1.16413565e+01 0. 0. 0.
    0. 0. 0. 0. 0. 0. 0. 0.</data></globfeat>
</opencv_storage>
